PercipioScrapPack/__init__.py
PercipioScrapPack/main.py
PercipioScrapPack-0.0.7.dist-info/METADATA
PercipioScrapPack-0.0.7.dist-info/WHEEL
PercipioScrapPack-0.0.7.dist-info/entry_points.txt
PercipioScrapPack-0.0.7.dist-info/top_level.txt
PercipioScrapPack-0.0.7.dist-info/RECORD
